MM18021UNO/__init__.py
MM18021UNO/biseccion.py
MM18021UNO/cramer.py
MM18021UNO/gauss.py
MM18021UNO/gauss_jordan.py
MM18021UNO/gauss_seidel.py
MM18021UNO/jacobi.py
MM18021UNO/lu.py
MM18021UNO/saludo.py
mm18021uno-0.1.1.dist-info/licenses/LICENSE
mm18021uno-0.1.1.dist-info/METADATA
mm18021uno-0.1.1.dist-info/WHEEL
mm18021uno-0.1.1.dist-info/top_level.txt
mm18021uno-0.1.1.dist-info/RECORD
